pdf_modifier_mcp/__init__.py
pdf_modifier_mcp/__main__.py
pdf_modifier_mcp/core/__init__.py
pdf_modifier_mcp/core/analyzer.py
pdf_modifier_mcp/core/exceptions.py
pdf_modifier_mcp/core/models.py
pdf_modifier_mcp/core/modifier.py
pdf_modifier_mcp/interfaces/__init__.py
pdf_modifier_mcp/interfaces/cli.py
pdf_modifier_mcp/interfaces/mcp.py
pdf_modifier_mcp-1.0.3.dist-info/LICENSE
pdf_modifier_mcp-1.0.3.dist-info/METADATA
pdf_modifier_mcp-1.0.3.dist-info/WHEEL
pdf_modifier_mcp-1.0.3.dist-info/entry_points.txt
pdf_modifier_mcp-1.0.3.dist-info/RECORD
