Metadata-Version: 2.3
Name: pdf-modifier-mcp
Version: 1.0.3
Summary: PDF modification tool with CLI and MCP interfaces for AI agents.
License: MIT
Keywords: pdf,mcp,claude,ai,modification
Author: Manu
Author-email: mlorentedev@gmail.com
Requires-Python: >=3.10
Classifier: Development Status :: 4 - Beta
Classifier: Intended Audience :: Developers
Classifier: Programming Language :: Python :: 3
Classifier: Programming Language :: Python :: 3.10
Classifier: Programming Language :: Python :: 3.11
Classifier: Programming Language :: Python :: 3.12
Classifier: Topic :: Text Processing :: General
Provides-Extra: dev
Requires-Dist: fastmcp (>=0.1.0)
Requires-Dist: mypy (>=1.0.0) ; extra == "dev"
Requires-Dist: pydantic (>=2.0.0)
Requires-Dist: pymupdf (>=1.26.7)
Requires-Dist: pytest (>=7.0.0) ; extra == "dev"
Requires-Dist: pytest-asyncio (>=0.23.0) ; extra == "dev"
Requires-Dist: pytest-cov (>=4.0.0) ; extra == "dev"
Requires-Dist: ruff (>=0.1.0) ; extra == "dev"
Requires-Dist: typer[all] (>=0.9.0)
